cpumarkets/__init__.py
cpumarkets/cli.py
cpumarkets/client.py
cpumarkets-0.1.0.dist-info/METADATA
cpumarkets-0.1.0.dist-info/WHEEL
cpumarkets-0.1.0.dist-info/entry_points.txt
cpumarkets-0.1.0.dist-info/top_level.txt
cpumarkets-0.1.0.dist-info/RECORD
