Metadata-Version: 2.4
Name: cpumarkets
Version: 0.1.0
Summary: CPUMarkets SDK and CLI for renting CPU compute
Author: CPUMarkets
License: Proprietary
Keywords: cpu,compute,marketplace,distributed,sdk
Classifier: Programming Language :: Python :: 3
Classifier: License :: Other/Proprietary License
Classifier: Operating System :: POSIX :: Linux
Requires-Python: >=3.8
